barp/__init__.py
barp/reflection.py
barp/system.py
barp/arg_builders/__init__.py
barp/arg_builders/base.py
barp/arg_builders/docker.py
barp/arg_builders/factory.py
barp/arg_builders/system_command.py
barp/cli/__init__.py
barp/cli/main.py
barp/cli/commands/__init__.py
barp/cli/commands/run.py
barp/operations/__init__.py
barp/operations/run.py
barp-0.0.1.dist-info/METADATA
barp-0.0.1.dist-info/WHEEL
barp-0.0.1.dist-info/entry_points.txt
barp-0.0.1.dist-info/licenses/LICENSE
barp-0.0.1.dist-info/RECORD
