Metadata-Version: 2.4
Name: barp
Version: 0.0.1
Summary: Build Arguments, Launch Process. A process launcher tool
Project-URL: Homepage, https://github.com/ignytis/barp
Author-email: Ignytis <155588001+ignytis@users.noreply.github.com>
License-Expression: MIT
License-File: LICENSE
Classifier: License :: OSI Approved :: MIT License
Classifier: Operating System :: OS Independent
Classifier: Programming Language :: Python :: 3
Requires-Python: >=3.13
Requires-Dist: configtpl~=1.0.0
Provides-Extra: cli
Requires-Dist: click<9.0.0,>=8.1.8; extra == 'cli'
